ai_shared/__init__.py
ai_shared/models.py
ai_shared-0.1.0.dist-info/METADATA
ai_shared-0.1.0.dist-info/WHEEL
ai_shared-0.1.0.dist-info/top_level.txt
ai_shared-0.1.0.dist-info/RECORD
