Metadata-Version: 2.4
Name: ai-shared
Version: 0.1.0
Summary: Add your description here
Requires-Python: >=3.13
Requires-Dist: numpy>=2.2.6
Requires-Dist: pydantic>=2.11.7
Requires-Dist: ultralytics>=8.3.193
